fractalpy/__init__.py
fractalpy/__main__.py
fractalpy/cli/__init__.py
fractalpy/cli/cli_main.py
fractalpy/cli/commands/__init__.py
fractalpy/cli/commands/cmd_fractal_base.py
fractalpy/cli/commands/cmd_julia.py
fractalpy/cli/commands/cmd_mandelbrot.py
fractalpy/cli/helper.py
fractalpy/fractals/__init__.py
fractalpy/fractals/fractal_base.py
fractalpy/fractals/fractals.py
fractalpy-0.1.1.dist-info/WHEEL
fractalpy-0.1.1.dist-info/entry_points.txt
fractalpy-0.1.1.dist-info/METADATA
fractalpy-0.1.1.dist-info/RECORD
