Metadata-Version: 2.1
Name: fractalpy
Version: 0.1.1
Summary: A high performance framework for fractal image and video generation
Home-page: https://github.com/Fergus-OH/FractalPy
License: MIT
Author: Fergus O'Hanlon
Author-email: fergusohanlon@gmail.com
Requires-Python: >=3.10,<3.11
Classifier: License :: OSI Approved :: MIT License
Classifier: Programming Language :: Python :: 3
Classifier: Programming Language :: Python :: 3.10
Requires-Dist: click (>=8.1.3,<9.0.0)
Requires-Dist: imageio (>=2.22.4,<3.0.0)
Requires-Dist: matplotlib (>=3.6.2,<4.0.0)
Requires-Dist: mpire (>=2.6.0,<3.0.0)
Requires-Dist: numba (>=0.56.4,<0.57.0)
Requires-Dist: numpy (>=1.23.5,<2.0.0)
Requires-Dist: pytest (>=7.2.0,<8.0.0)
Requires-Dist: pytest-cov (>=4.0.0,<5.0.0)
Requires-Dist: sphinx (>=5.3.0,<6.0.0)
Requires-Dist: sphinx-rtd-theme (>=1.1.1,<2.0.0)
Requires-Dist: sphinxcontrib-napoleon (>=0.7,<0.8)
Project-URL: Bug Tracker, https://github.com/Fergus-OH/FractalPy/issues
Project-URL: Repository, https://github.com/Fergus-OH/FractalPy
